{"version": 0.6, "generator": "Overpass API 0.7.62.1 084b4234", "osm3s": {"timestamp_osm_base": "2024-05-23T15:38:10Z", "copyright": "The data included in this document is from www.openstreetmap.org. The data is made available under ODbL."}, "elements": [{"type": "node", "id": 6053546209, "lat": 45.8638733, "lon": 22.9081048, "tags": {"amenity": "clinic"}}, {"type": "node", "id": 6053546288, "lat": 45.8803245, "lon": 22.896728, "tags": {"amenity": "clinic"}}, {"type": "node", "id": 6053546295, "lat": 45.8799143, "lon": 22.9033227, "tags": {"amenity": "clinic"}}, {"type": "node", "id": 11254642054, "lat": 45.8780847, "lon": 22.9059738, "tags": {"amenity": "clinic", "contact:email": "deva@affidea.com", "contact:phone": "+40 354 802 070;+40 738 470 002", "contact:website": "https://affidea.ro/centre-medicale/phoenix-deva", "name": "Affidea", "opening_hours": "Mo-Fr 08:00-20:00"}}]}