{"version": 0.6, "generator": "Overpass API 0.7.62.1 084b4234", "osm3s": {"timestamp_osm_base": "2024-05-23T17:02:16Z", "copyright": "The data included in this document is from www.openstreetmap.org. The data is made available under ODbL."}, "elements": [{"type": "node", "id": 4253211789, "lat": 46.1628284, "lon": 24.3483151, "tags": {"addr:housenumber": "13", "addr:postcode": "551003", "addr:street": "Strada Pet\u00f6fi Sandor", "amenity": "clinic", "name": "SC Lotus Med"}}, {"type": "node", "id": 11586576854, "lat": 46.1630949, "lon": 24.3564856, "tags": {"amenity": "clinic", "contact:email": "medias@affidea.com", "contact:phone": "+40 269 838 131;+40 269 838 132;+40 369 425 086", "contact:website": "https://affidea.ro/", "name": "Affidea", "opening_hours": "Mo-Fr 08:00-20:00"}}]}