{"version": 0.6, "generator": "Overpass API 0.7.62.1 084b4234", "osm3s": {"timestamp_osm_base": "2024-05-23T16:09:33Z", "copyright": "The data included in this document is from www.openstreetmap.org. The data is made available under ODbL."}, "elements": [{"type": "node", "id": 2223247710, "lat": 45.40737, "lon": 23.3765862}, {"type": "node", "id": 2223247714, "lat": 45.4071408, "lon": 23.3761208}, {"type": "node", "id": 2223247717, "lat": 45.4072607, "lon": 23.376012}, {"type": "node", "id": 2223247720, "lat": 45.4071459, "lon": 23.3765911}, {"type": "node", "id": 2223247722, "lat": 45.407615, "lon": 23.3764124}, {"type": "node", "id": 2223247726, "lat": 45.4072634, "lon": 23.376259}, {"type": "node", "id": 2223247729, "lat": 45.4076132, "lon": 23.3762514}, {"type": "node", "id": 2223247732, "lat": 45.4072619, "lon": 23.3761181}, {"type": "node", "id": 2223247734, "lat": 45.4079933, "lon": 23.3759961}, {"type": "node", "id": 2223247736, "lat": 45.4073665, "lon": 23.3762568}, {"type": "node", "id": 2223247738, "lat": 45.4077601, "lon": 23.3762234}, {"type": "node", "id": 2223247740, "lat": 45.4079957, "lon": 23.3762182}, {"type": "node", "id": 2223247742, "lat": 45.4077621, "lon": 23.3764092}, {"type": "node", "id": 2584715598, "lat": 45.4080134, "lon": 23.3754804}, {"type": "node", "id": 2584715599, "lat": 45.4082011, "lon": 23.3754743}, {"type": "node", "id": 2584715600, "lat": 45.4082023, "lon": 23.3755478}, {"type": "node", "id": 2584715601, "lat": 45.4082318, "lon": 23.3758288}, {"type": "node", "id": 2584715602, "lat": 45.4082273, "lon": 23.375547}, {"type": "node", "id": 2584715603, "lat": 45.4080191, "lon": 23.3758357}, {"type": "node", "id": 4411414070, "lat": 45.4152681, "lon": 23.3728055, "tags": {"amenity": "clinic", "healthcare": "clinic", "name": "Cabinet Medical Udrea-Iona\u0219cu"}}, {"type": "node", "id": 4679572504, "lat": 45.3844991, "lon": 23.4715182, "tags": {"amenity": "clinic", "healthcare": "clinic", "name": "Salvamont Par\u00e2ng", "name:ro": "Salvamont Par\u00e2ng", "phone": "0725826668"}}, {"type": "node", "id": 7653380598, "lat": 45.4076751, "lon": 23.376003, "tags": {"door": "yes", "entrance": "main"}}, {"type": "node", "id": 7653380599, "lat": 45.4073548, "lon": 23.37601, "tags": {"door": "yes/manual", "entrance": "emergency"}}, {"type": "node", "id": 7653380600, "lat": 45.4082296, "lon": 23.3756879, "tags": {"entrance": "yes"}}, {"type": "node", "id": 10207121415, "lat": 45.4090994, "lon": 23.3750213, "tags": {"amenity": "clinic", "healthcare": "clinic", "name": "Alma Med"}}, {"type": "node", "id": 10881980018, "lat": 45.4080928, "lon": 23.3764126}, {"type": "node", "id": 10881980019, "lat": 45.4075147, "lon": 23.3764249}, {"type": "node", "id": 10881980020, "lat": 45.4075202, "lon": 23.376951}, {"type": "node", "id": 10881980021, "lat": 45.4076295, "lon": 23.3767907}, {"type": "node", "id": 10881980022, "lat": 45.4076283, "lon": 23.3765695}, {"type": "node", "id": 10881980023, "lat": 45.4077162, "lon": 23.37657}, {"type": "node", "id": 10881980024, "lat": 45.4077175, "lon": 23.3767884}, {"type": "node", "id": 10881980025, "lat": 45.4078139, "lon": 23.3767853}, {"type": "node", "id": 10881980026, "lat": 45.4078123, "lon": 23.3765705}, {"type": "node", "id": 10881980027, "lat": 45.4079813, "lon": 23.3765714}, {"type": "node", "id": 10881980028, "lat": 45.4079825, "lon": 23.3767798}, {"type": "node", "id": 10881980029, "lat": 45.4080983, "lon": 23.3769354}, {"type": "node", "id": 10881980030, "lat": 45.4080937, "lon": 23.3764955, "tags": {"entrance": "yes"}}, {"type": "node", "id": 10881980031, "lat": 45.4080973, "lon": 23.3768374, "tags": {"entrance": "yes"}}, {"type": "node", "id": 10881980033, "lat": 45.4076295, "lon": 23.3767844}, {"type": "node", "id": 10881980035, "lat": 45.407534, "lon": 23.3769506}, {"type": "way", "id": 212487148, "nodes": [2223247732, 2223247726, 2223247736, 2223247729, 2223247722, 2223247742, 2223247738, 2223247740, 2223247734, 7653380598, 7653380599, 2223247717, 2223247732], "tags": {"addr:city": "Petro\u0219ani", "addr:housenumber": "137 A", "addr:postcode": "332058", "addr:street": "Strada 1 Decembrie 1918", "amenity": "hospital", "building": "yes", "healthcare": "hospital", "healthcare:speciality": "psychiatry;paediatrics;gynaecology;cardiology;oncology;emergency;surgery;internal;maternity;radiology;orthopaedics;dialysis", "name": "Spitalul de Urgen\u021b\u0103", "operator": "Ministerul Sanatatii", "operator:type": "public"}}, {"type": "way", "id": 248001511, "nodes": [2223247732, 2223247714, 2223247720, 2223247710, 2223247736, 2223247726, 2223247732], "tags": {"addr:city": "Petro\u0219ani", "addr:housenumber": "137 A", "addr:postcode": "332058", "addr:street": "Strada 1 Decembrie 1918", "amenity": "hospital", "building": "yes", "emergency": "yes", "name": "Spitalul de Urgen\u021b\u0103"}}, {"type": "way", "id": 252411984, "nodes": [2584715599, 2584715598, 2584715603, 2584715601, 7653380600, 2584715602, 2584715600, 2584715599], "tags": {"amenity": "clinic", "building": "yes", "contact:email": "petrosani@affidea.com", "contact:phone": "+40 21 9338", "contact:website": "https://affidea.ro/centre-medicale/affidea-petrosani", "healthcare": "hospital", "healthcare:speciality": "dialysis", "name": "Affidea", "opening_hours": "Mo-Fr 08:00-20:00"}}, {"type": "way", "id": 1171003449, "nodes": [10881980018, 10881980019, 10881980020, 10881980021, 10881980033, 10881980022, 10881980023, 10881980024, 10881980025, 10881980026, 10881980027, 10881980028, 10881980029, 10881980031, 10881980030, 10881980018], "tags": {"amenity": "clinic", "building": "yes", "healthcare": "clinic", "name": "Policlinic\u0103"}}, {"type": "way", "id": 1171003450, "nodes": [10881980029, 10881980028, 10881980025, 10881980024, 10881980021, 10881980020, 10881980035, 10881980029], "tags": {"amenity": "clinic", "building": "yes", "healthcare": "clinic", "name": "Policlinic\u0103"}}]}